[
    {
        "iconUrl": "https://www.google.com/s2/favicons?domain=nguonc.com&sz=%size%",
        "apiVersion": 1,
        "repositoryUrl": "https://github.com/osxcrk/repophim",
        "fileSize": 15436,
        "status": 1,
        "language": "vi",
        "authors": [
            "Hexated, Unknow8x"
        ],
        "tvTypes": [
            "AnimeMovie",
            "Anime",
            "TvSeries",
            "Movie",
            "OVA"
        ],
        "version": 1,
        "internalName": "NguonCProvider",
        "url": "https://raw.githubusercontent.com/osxcrk/repophim/builds/NguonCProvider.cs3",
        "name": "NguonCProvider"
    },
    {
        "iconUrl": "https://www.google.com/s2/favicons?domain=bilutvb.org&sz=%size%",
        "apiVersion": 1,
        "repositoryUrl": "https://github.com/osxcrk/repophim",
        "fileSize": 15436,
        "status": 1,
        "language": "vi",
        "authors": [
            "Hexated, Unknow8x"
        ],
        "tvTypes": [
            "AnimeMovie",
            "Anime",
            "TvSeries",
            "Movie",
            "OVA"
        ],
        "version": 1,
        "internalName": "BilutvProvider",
        "url": "https://raw.githubusercontent.com/osxcrk/repophim/builds/BilutvProvider.cs3",
        "name": "BilutvProvider"
    },
    {
        "iconUrl": "https://chillhay.im/wp-content/uploads/2023/06/ChillhayIn.png",
        "apiVersion": 1,
        "repositoryUrl": "https://github.com/osxcrk/repophim",
        "fileSize": 15553,
        "status": 0,
        "language": "vi",
        "authors": [
            "Blue, osxcrk"
        ],
        "tvTypes": [
            "AsianDrama",
            "Anime",
            "TvSeries",
            "Movie"
        ],
        "version": 5,
        "internalName": "ChillhayProvider",
        "description": "#Chillhay Phim Thuy\u1ebft Minh",
        "url": "https://raw.githubusercontent.com/osxcrk/repophim/builds/ChillhayProvider.cs3",
        "name": "ChillhayProvider"
    },
    {
        "iconUrl": "https://play-lh.googleusercontent.com/TOTj0uMWp7cXkjXDXkcTZnPigUmpLRRiH956lHRJxStlY7ucxmtwMs_Kr2wOWYm0fSY=w240-h480-rw",
        "apiVersion": 1,
        "repositoryUrl": "https://github.com/osxcrk/repophim",
        "fileSize": 21097,
        "status": 1,
        "language": "vi",
        "authors": [
            "Blue"
        ],
        "tvTypes": [
            "Movie"
        ],
        "version": 4,
        "internalName": "FshareProvider",
        "description": "Fshare 4K Bluray , 2k ,1080P \u0111\u1ee7 th\u1ec3 lo\u1ea1i. Bu\u1ed5i t\u1ed1i ae k\u00e9o nhi\u1ec1u h\u01a1i lag :3",
        "url": "https://raw.githubusercontent.com/osxcrk/repophim/builds/FshareProvider.cs3",
        "name": "FshareProvider"
    },
    {
        "iconUrl": "https://www.google.com/s2/favicons?domain=loklok.com&sz=%size%",
        "apiVersion": 1,
        "repositoryUrl": "https://github.com/osxcrk/repophim",
        "fileSize": 22972,
        "status": 1,
        "language": "vi",
        "authors": [
            "Blue"
        ],
        "tvTypes": [
            "AsianDrama",
            "Anime",
            "TvSeries",
            "Movie"
        ],
        "version": 3,
        "internalName": "OphimProvider",
        "description": "#Ophim API",
        "url": "https://raw.githubusercontent.com/osxcrk/repophim/builds/OphimProvider.cs3",
        "name": "OphimProvider"
    },
    {
        "iconUrl": "https://www.google.com/s2/favicons?domain=xem1080.com",
        "apiVersion": 1,
        "repositoryUrl": "https://github.com/osxcrk/repophim",
        "fileSize": 21308,
        "status": 1,
        "language": "vi",
        "authors": [
            "TuaSan"
        ],
        "tvTypes": [
            "AsianDrama",
            "Anime",
            "TvSeries",
            "Movie"
        ],
        "version": 2,
        "internalName": "Phim1080",
        "description": "Xem Phim Online Ch\u1ea5t L\u01b0\u1ee3ng Cao",
        "url": "https://raw.githubusercontent.com/osxcrk/repophim/builds/Phim1080.cs3",
        "name": "Phim1080"
    },
    {
        "iconUrl": "https://www.google.com/s2/favicons?domain=phimmoichilld.net&sz=%size%",
        "apiVersion": 1,
        "repositoryUrl": "https://github.com/osxcrk/repophim",
        "fileSize": 15788,
        "status": 1,
        "language": "vi",
        "authors": [
            "TuaSan"
        ],
        "tvTypes": [
            "AsianDrama",
            "Anime",
            "TvSeries",
            "Movie"
        ],
        "version": 12,
        "internalName": "Phimmoichill",
        "url": "https://raw.githubusercontent.com/osxcrk/repophim/builds/Phimmoichill.cs3",
        "name": "Phimmoichill"
    },
    {
        "iconUrl": "https://raw.githubusercontent.com/hexated/cloudstream-extensions-hexated/master/SoraStream/Icon.png",
        "apiVersion": 1,
        "repositoryUrl": "https://github.com/osxcrk/repophim",
        "fileSize": 297583,
        "status": 1,
        "language": "vi",
        "authors": [
            "Hexated",
            "Sora",
            "TuaSan"
        ],
        "tvTypes": [
            "AsianDrama",
            "TvSeries",
            "Anime",
            "Movie"
        ],
        "version": 33,
        "internalName": "SoraStreamVn",
        "description": "#1 best extention based on MultiAPI",
        "url": "https://raw.githubusercontent.com/osxcrk/repophim/builds/SoraStreamVn.cs3",
        "name": "SoraStreamVn"
    },
    {
        "iconUrl": "https://subnhanh.vip/logo1.png",
        "apiVersion": 1,
        "repositoryUrl": "https://github.com/osxcrk/repophim",
        "fileSize": 14751,
        "status": 1,
        "language": "vi",
        "authors": [
            "Blue"
        ],
        "tvTypes": [
            "AsianDrama",
            "Anime",
            "TvSeries",
            "Movie"
        ],
        "version": 2,
        "internalName": "SubnhanhProvider",
        "description": "#Subnhanh",
        "url": "https://raw.githubusercontent.com/osxcrk/repophim/builds/SubnhanhProvider.cs3",
        "name": "SubnhanhProvider"
    },
    {
        "iconUrl": "https://www.google.com/s2/favicons?domain=tocanime.co&sz=%size%",
        "apiVersion": 1,
        "repositoryUrl": "https://github.com/osxcrk/repophim",
        "fileSize": 13898,
        "status": 1,
        "language": "vi",
        "authors": [
            "Hexated, TuaSan"
        ],
        "tvTypes": [
            "AnimeMovie",
            "Anime",
            "OVA"
        ],
        "version": 2,
        "internalName": "TocanimeProvider",
        "url": "https://raw.githubusercontent.com/osxcrk/repophim/builds/TocanimeProvider.cs3",
        "name": "TocanimeProvider"
    },
    {
        "iconUrl": "https://tvhayb.org/Theme/images/icon-tvhay-fb-1024.png",
        "apiVersion": 1,
        "repositoryUrl": "https://github.com/osxcrk/repophim",
        "fileSize": 15532,
        "status": 0,
        "language": "vi",
        "authors": [
            "Blue, Unknow8x"
        ],
        "tvTypes": [
            "AsianDrama",
            "Anime",
            "TvSeries",
            "Movie"
        ],
        "version": 4,
        "internalName": "TvHayProvider",
        "description": "#TVHay Phim Thuy\u1ebft Minh",
        "url": "https://raw.githubusercontent.com/osxcrk/repophim/builds/TvHayProvider.cs3",
        "name": "TvHayProvider"
    },
    {
        "iconUrl": "https://xem8z.com/wp-content/uploads/2023/06/movievideoicon-1320087274946223173.png",
        "apiVersion": 1,
        "repositoryUrl": "https://github.com/osxcrk/repophim",
        "fileSize": 15532,
        "status": 1,
        "language": "vi",
        "authors": [
            "Blue, Unknow8x"
        ],
        "tvTypes": [
            "AsianDrama",
            "Anime",
            "TvSeries",
            "Movie"
        ],
        "version": 1,
        "internalName": "xem8zProvider",
        "description": "#Xem8z Phim Thuy\u1ebft Minh",
        "url": "https://raw.githubusercontent.com/osxcrk/repophim/builds/Xem8z.cs3",
        "name": "xem8zProvider"
    },
    {
        "iconUrl": "https://bluphim.com/Content/BluPhim/Imgs/bluphim2.png",
        "apiVersion": 1,
        "repositoryUrl": "https://github.com/osxcrk/repophim",
        "fileSize": 15532,
        "status": 1,
        "language": "vi",
        "authors": [
            "Blue, Unknow8x"
        ],
        "tvTypes": [
            "AsianDrama",
            "Anime",
            "TvSeries",
            "Movie"
        ],
        "version": 4,
        "internalName": "BluphimProvider",
        "description": "#Bluphim Phim Thuy\u1ebft Minh",
        "url": "https://raw.githubusercontent.com/osxcrk/repophim/builds/Bluphim.cs3",
        "name": "BluphimProvider"
    },
     {
        "iconUrl": "https://encrypted-tbn0.gstatic.com/images?q=tbn:ANd9GcTVXgt1ROWUjrXsmdPpum1ql3IGegwcagLeNZsiSO0J&s",
        "apiVersion": 1,
        "repositoryUrl": "https://github.com/osxcrk/repophim",
        "fileSize": 41610,
        "status": 1,
        "language": "vi",
        "authors": [
            "Blue"
        ],
        "tvTypes": [
            "AsianDrama",
            "TvSeries",
            "Movie"
        ],
        "version": 1,
        "internalName": "BongNgoTVProvider",
        "description": "#1",
        "url": "https://raw.githubusercontent.com/duongnv1996/bongngo-cs3-extension/builds/BongNgoTVProvider.cs3",
        "name": "BongNgoTVProvider"
    },
    {
        "iconUrl": "https://www.google.com/s2/favicons?domain=youtube.com&sz=%size%",
        "apiVersion": 1,
        "repositoryUrl": "https://github.com/osxcrk/repophim",
        "fileSize": 11610,
        "status": 1,
        "language": "vi",
        "authors": [
            "Blue, osxcrk"
        ],
        "tvTypes": [
            "AsianDrama",
            "TvSeries",
            "Movie",
            "Others"
        ],
        "version": 1,
        "internalName": "BongNgoTVProvider",
        "description": "#1",
        "url": "https://raw.githubusercontent.com/duongnv1996/bongngo-cs3-extension/builds/BongNgoTVProvider.cs3",
        "name": "BongNgoTVProvider"
    }
]
